wzm/__init__.py
wzm/client.py
wzm/config.py
wzm/core.py
wzm/finance.py
wzm/net.py
wzm/py.typed
wzm-0.2.0.dist-info/METADATA
wzm-0.2.0.dist-info/WHEEL
wzm-0.2.0.dist-info/entry_points.txt
wzm-0.2.0.dist-info/top_level.txt
wzm-0.2.0.dist-info/RECORD
