Metadata-Version: 2.4
Name: wzm
Version: 0.2.0
Summary: A typed demo SDK with rich docstrings and a minimal HTTP client.
Author-email: Demo <demo@example.com>
License: MIT
Requires-Python: >=3.9
Requires-Dist: pandas>=1.5
Requires-Dist: requests>=2.31
Requires-Dist: typing-extensions>=4.8
